aiofcm/__init__.py
aiofcm/client.py
aiofcm/common.py
aiofcm/connection.py
aiofcm/errors.py
aiofcm/exceptions.py
aiofcm/logging.py
aiofcm/py.typed
aiofcm-1.4.dist-info/LICENSE
aiofcm-1.4.dist-info/METADATA
aiofcm-1.4.dist-info/WHEEL
aiofcm-1.4.dist-info/top_level.txt
aiofcm-1.4.dist-info/RECORD
