Metadata-Version: 2.1
Name: aiofcm
Version: 1.4
Summary: An efficient Firebase Cloud Messaging Client Library for Python/asyncio
Home-page: https://github.com/Fatal1ty/aiofcm
Author: Alexander Tikhonov
Author-email: random.gauss@gmail.com
License: Apache License, Version 2.0
Platform: all
Classifier: License :: OSI Approved :: Apache Software License
Classifier: Intended Audience :: Developers
Classifier: Operating System :: MacOS :: MacOS X
Classifier: Operating System :: POSIX
Classifier: Programming Language :: Python :: 3 :: Only
Classifier: Programming Language :: Python :: 3.5
Classifier: Programming Language :: Python :: 3.6
Classifier: Programming Language :: Python :: 3.7
Classifier: Programming Language :: Python :: 3.8
Classifier: Programming Language :: Python :: 3.9
Classifier: Programming Language :: Python :: 3.10
Classifier: Programming Language :: Python :: 3.11
Classifier: Development Status :: 5 - Production/Stable
License-File: LICENSE
Requires-Dist: aioxmpp (>=0.10)
